{
  "/*404": [
    {
      "type": "script",
      "href": "https://lwinmoepaing.github.io/assets/_...404_-e28ed339.js"
    },
    {
      "type": "script",
      "href": "https://lwinmoepaing.github.io/assets/entry-client-71598ae6.js"
    },
    {
      "type": "style",
      "href": "https://lwinmoepaing.github.io/assets/entry-client-616abe02.css"
    }
  ],
  "/about/": [
    {
      "type": "script",
      "href": "https://lwinmoepaing.github.io/assets/index-64c9a0e1.js"
    },
    {
      "type": "script",
      "href": "https://lwinmoepaing.github.io/assets/entry-client-71598ae6.js"
    },
    {
      "type": "style",
      "href": "https://lwinmoepaing.github.io/assets/entry-client-616abe02.css"
    }
  ],
  "/blog/": [
    {
      "type": "script",
      "href": "https://lwinmoepaing.github.io/assets/index-706f8b76.js"
    },
    {
      "type": "script",
      "href": "https://lwinmoepaing.github.io/assets/entry-client-71598ae6.js"
    },
    {
      "type": "style",
      "href": "https://lwinmoepaing.github.io/assets/entry-client-616abe02.css"
    },
    {
      "type": "script",
      "href": "https://lwinmoepaing.github.io/assets/MetaHead-6d8556a7.js"
    }
  ],
  "/blog/one": [
    {
      "type": "script",
      "href": "https://lwinmoepaing.github.io/assets/one-e9110999.js"
    },
    {
      "type": "script",
      "href": "https://lwinmoepaing.github.io/assets/entry-client-71598ae6.js"
    },
    {
      "type": "style",
      "href": "https://lwinmoepaing.github.io/assets/entry-client-616abe02.css"
    }
  ],
  "/books/": [
    {
      "type": "script",
      "href": "https://lwinmoepaing.github.io/assets/index-014e041e.js"
    },
    {
      "type": "script",
      "href": "https://lwinmoepaing.github.io/assets/entry-client-71598ae6.js"
    },
    {
      "type": "style",
      "href": "https://lwinmoepaing.github.io/assets/entry-client-616abe02.css"
    },
    {
      "type": "script",
      "href": "https://lwinmoepaing.github.io/assets/MetaHead-6d8556a7.js"
    }
  ],
  "/": [
    {
      "type": "script",
      "href": "https://lwinmoepaing.github.io/assets/index-f70e43b5.js"
    },
    {
      "type": "script",
      "href": "https://lwinmoepaing.github.io/assets/entry-client-71598ae6.js"
    },
    {
      "type": "style",
      "href": "https://lwinmoepaing.github.io/assets/entry-client-616abe02.css"
    },
    {
      "type": "script",
      "href": "https://lwinmoepaing.github.io/assets/MetaHead-6d8556a7.js"
    }
  ],
  "/sharing/catch-22-experience": [
    {
      "type": "script",
      "href": "https://lwinmoepaing.github.io/assets/catch-22-experience-73f123a5.js"
    },
    {
      "type": "script",
      "href": "https://lwinmoepaing.github.io/assets/entry-client-71598ae6.js"
    },
    {
      "type": "style",
      "href": "https://lwinmoepaing.github.io/assets/entry-client-616abe02.css"
    }
  ],
  "/sharing/": [
    {
      "type": "script",
      "href": "https://lwinmoepaing.github.io/assets/index-7cb8864c.js"
    },
    {
      "type": "script",
      "href": "https://lwinmoepaing.github.io/assets/entry-client-71598ae6.js"
    },
    {
      "type": "style",
      "href": "https://lwinmoepaing.github.io/assets/entry-client-616abe02.css"
    },
    {
      "type": "script",
      "href": "https://lwinmoepaing.github.io/assets/MetaHead-6d8556a7.js"
    }
  ],
  "entry-client": [
    {
      "type": "script",
      "href": "https://lwinmoepaing.github.io/assets/entry-client-71598ae6.js"
    },
    {
      "type": "style",
      "href": "https://lwinmoepaing.github.io/assets/entry-client-616abe02.css"
    }
  ],
  "index.html": []
}